wellaware/__init__.py
wellaware/_compat.py
wellaware/client.py
wellaware/constants.py
wellaware/VERSION
wellaware/auth/__init__.py
wellaware/auth/auth_roles.py
wellaware/auth/token.py
wellaware/auth/token_resource.py
wellaware/base/__init__.py
wellaware/base/base_entity.py
wellaware/base/base_resource.py
wellaware/exceptions/__init__.py
wellaware/exceptions/api_exception.py
wellaware/exceptions/api_unavailable_exception.py
wellaware/exceptions/client_exception.py
wellaware/exceptions/forbidden_exception.py
wellaware/exceptions/invalid_input_exception.py
wellaware/exceptions/not_found_exception.py
wellaware/exceptions/requires_login_exception.py
wellaware/exceptions/server_exception.py
wellaware/exceptions/timeout_exception.py
wellaware/exceptions/token_expired_exception.py
wellaware/exceptions/unexpected_response_exception.py
wellaware/patterns/__init__.py
wellaware/patterns/assets.py
wellaware/resources/__init__.py
wellaware/resources/common.py
wellaware/resources/assets/__init__.py
wellaware/resources/assets/models.py
wellaware/resources/assets/resource.py
wellaware/resources/controlaudits/__init__.py
wellaware/resources/controlaudits/models.py
wellaware/resources/controlaudits/resource.py
wellaware/resources/controlpoints/__init__.py
wellaware/resources/controlpoints/models.py
wellaware/resources/controlpoints/resource.py
wellaware/resources/controlrules/__init__.py
wellaware/resources/controlrules/models.py
wellaware/resources/controlrules/resource.py
wellaware/resources/data/__init__.py
wellaware/resources/data/data_errors.py
wellaware/resources/data/data_models.py
wellaware/resources/data/data_responses.py
wellaware/resources/data/resource.py
wellaware/resources/permissions/__init__.py
wellaware/resources/permissions/models.py
wellaware/resources/permissions/resource.py
wellaware/resources/points/__init__.py
wellaware/resources/points/models.py
wellaware/resources/points/resource.py
wellaware-1.2.10.dist-info/top_level.txt
wellaware-1.2.10.dist-info/dependency_links.txt
wellaware-1.2.10.dist-info/METADATA
wellaware-1.2.10.dist-info/DESCRIPTION.rst
wellaware-1.2.10.dist-info/metadata.json
wellaware-1.2.10.dist-info/WHEEL
wellaware-1.2.10.dist-info/RECORD
